{
    "header": [
        {"ColumnName": "ISSPLNT", "TextFormatMode": "ValueKey",
            "ValueHelp": {"show": true, "items": {"path": "issplant", "value": "PLANTCD", "text": "DESCRIPTION"},
                "SuggestionItems": {"path": "issplant>/", "text": "{issplant>PLANTCD}", "additionalText": "{issplant>DESCRIPTION}", "maxSuggestionWidth": "300px" },
                "columns": "tvh_issplnt"
            }
        },
        {"ColumnName": "SOLDTOCUST", "TextFormatMode": "ValueKey",
            "ValueHelp": {"show": true, "items": {"path": "soldtocust", "value": "CUSTOMER", "text": "NAME1"},
                "SuggestionItems": {"path": "soldtocust>/", "text": "{soldtocust>CUSTOMER}", "additionalText": "{soldtocust>NAME1}",  "maxSuggestionWidth": "300px"},
                "columns": "tvh_soldtocust"
            }
        },
        {"ColumnName": "BILLTOCUST", "TextFormatMode": "ValueKey",
            "ValueHelp": {"show": true, "items": {"path": "shiptocust", "value": "CUSTOMER", "text": "NAME1"},
                "SuggestionItems": {"path": "shiptocust>/", "text": "{shiptocust>CUSTOMER}", "additionalText": "{shiptocust>NAME1}",  "maxSuggestionWidth": "400px"},
                "columns": "tvh_billtocust"
            }
        },
        {"ColumnName": "SALESTERM", 
            "ValueHelp": {"show": true, "items": {"path": "salesterm", "value": "SALESTERM", "text": "DESCRIPTION" },
                "SuggestionItems": {"path": "salesterm>/", "text": "{salesterm>SALESTERM}", "additionalText": "{salesterm>DESCRIPTION}", "maxSuggestionWidth": "300px"},
                "columns": "tvh_salesterm"
            }
        },
        {"ColumnName": "EVERS", "TextFormatMode": "ValueKey",
            "ValueHelp": {"show": true, "items": {"path": "shipmode", "value": "SHIPMODE", "text": "DESCRIPTION"},
                "SuggestionItems": {"path": "shipmode>/", "text": "{shipmode>SHIPMODE}", "additionalText": "{shipmode>DESCRIPTION}", "maxSuggestionWidth": "200px"},
                "columns": "tvh_evers"
            }
        },
        {"ColumnName": "DEST", "TextFormatMode": "ValueKey",
            "ValueHelp": {"show": true, "items": {"path": "dest", "value": "DESTCD", "text": "DESC1"},
                "SuggestionItems": {"path": "dest>/", "text": "{dest>DESTCD}", "additionalText": "{dest>DESC1}", "maxSuggestionWidth": "200px"},
                "columns": "tvh_dest"
            }
        },
        {"ColumnName": "CONSIGN", 
            "ValueHelp": {"show": true, "items": {"path": "consign", "value": "CONSIGNCD", "text": "CONSIGNCD"},
                "SuggestionItems": {"path": "consign>/", "text": "{consign>CONSIGNCD}", "additionalText": "{consign>ADDR1}", "maxSuggestionWidth": "200px"},
                "columns": "tvh_consign"
            }
        },
        {"ColumnName": "MESSRS", 
            "ValueHelp": {"show": true, "items": {"path": "consign", "value": "CONSIGNCD", "text": "CONSIGNCD"},
                "SuggestionItems": {"path": "consign>/", "text": "{consign>CONSIGNCD}", "additionalText": "{consign>ADDR1}", "maxSuggestionWidth": "200px"},
                "columns": "tvh_consign"
            }
        },
        {"ColumnName": "VOLUOM", "TextFormatMode": "ValueKey",
            "ValueHelp": {"show": true, "items": {"path": "voluom", "value": "UOM", "text": "DESCRIPTION"},
                "SuggestionItems": {"path": "voluom>/", "text": "{voluom>UOM}", "additionalText": "{voluom>DESCRIPTION}", "maxSuggestionWidth": "200px"},
                "columns": "tvh_uom"
            }
        },
        {"ColumnName": "WTUOM", "TextFormatMode": "ValueKey",
            "ValueHelp": {"show": true, "items": {"path": "wtuom", "value": "UOM", "text": "DESCRIPTION"},
                "SuggestionItems": {"path": "wtuom>/", "text": "{wtuom>UOM}", "additionalText": "{wtuom>DESCRIPTION}", "maxSuggestionWidth": "200px"},
                "columns": "tvh_uom"
            }
        },
        {"ColumnName": "ACCTTYP", "TextFormatMode": "ValueKey",
            "ValueHelp": {"show": true, "items": {"path": "acctyp", "value": "ACCTTYP", "text": "DESC1"},
                "SuggestionItems": {"path": "acctyp>/", "text": "{acctyp>ACCTTYP}", "additionalText": "{acctyp>DESC1}", "maxSuggestionWidth": "200px"},
                "columns": "tvh_acctyp"
            }
        },
        {"ColumnName": "STATUS", "TextFormatMode": "ValueKey",
            "ValueHelp": {"show": true, "items": {"path": "status", "value": "DLVSTATCD", "text": "SHORTTEXT"},
                "SuggestionItems": {"path": "status>/", "text": "{status>DLVSTATCD}", "additionalText": "{status>SHORTTEXT}", "maxSuggestionWidth": "200px"}
            }
        }
    ],
    "tvh_issplnt": [
        {"ColumnName": "PLANTCD", "DataType": "STRING", "ColumnWidth": "100px", "Visible": true, "Key": true, "Value": false},
        {"ColumnName": "DESCRIPTION", "DataType": "STRING", "ColumnWidth": "300px", "Visible": true, "Key": false, "Value": true}
    ],    
    "tvh_soldtocust": [
        {"ColumnName": "CUSTOMER", "DataType": "STRING", "ColumnWidth": "120px", "Visible": true, "Key": true, "Value": false},
        {"ColumnName": "NAME1", "DataType": "STRING", "ColumnWidth": "350px", "Visible": true, "Key": false, "Value": true},
        {"ColumnName": "CUSTGRP", "DataType": "STRING", "ColumnWidth": "80px", "Visible": true, "Key": false, "Value": false}
    ],
    "tvh_billtocust": [
        {"ColumnName": "CUSTOMER", "DataType": "STRING", "ColumnWidth": "120px", "Visible": true, "Key": true, "Value": false},
        {"ColumnName": "NAME1", "DataType": "STRING", "ColumnWidth": "350px", "Visible": true, "Key": false, "Value": true},
        {"ColumnName": "CUSTGRP", "DataType": "STRING", "ColumnWidth": "80px", "Visible": false, "Key": false, "Value": false}
    ],
    "tvh_salesterm": [
        {"ColumnName": "SALESTERM", "DataType": "STRING", "ColumnWidth": "150px", "Visible": true, "Key": true, "Value": true},
        {"ColumnName": "DESCRIPTION", "DataType": "STRING", "ColumnWidth": "250px", "Visible": true, "Key": false, "Value": false}
    ],
    "tvh_evers": [
        {"ColumnName": "SHIPMODE", "DataType": "STRING", "ColumnWidth": "150px", "Visible": true, "Key": true, "Value": false},
        {"ColumnName": "DESCRIPTION", "DataType": "STRING", "ColumnWidth": "250px", "Visible": true, "Key": false, "Value": true}
    ],
    "tvh_dest": [
        {"ColumnName": "DESTCD", "DataType": "STRING", "ColumnWidth": "100px", "Visible": true, "Key": true, "Value": false},
        {"ColumnName": "DESC1", "DataType": "STRING", "ColumnWidth": "300px", "Visible": true, "Key": false, "Value": true}
    ],
    "tvh_consign": [
        {"ColumnName": "CONSIGNCD", "DataType": "STRING", "ColumnWidth": "150px", "Visible": true, "Key": true, "Value": true},
        {"ColumnName": "ADDR1", "DataType": "STRING", "ColumnWidth": "500px", "Visible": true, "Key": false, "Value": false},
        {"ColumnName": "CUSTGRP", "DataType": "STRING", "ColumnWidth": "300px", "Visible": false, "Key": false, "Value": false}
    ],
    "tvh_uom": [
        {"ColumnName": "UOM", "DataType": "STRING", "ColumnWidth": "100px", "Visible": true, "Key": true, "Value": false},
        {"ColumnName": "DESCRIPTION", "DataType": "STRING", "ColumnWidth": "300px", "Visible": true, "Key": false, "Value": true}
    ],
    "tvh_acctyp": [
        {"ColumnName": "ACCTTYP", "DataType": "STRING", "ColumnWidth": "100px", "Visible": true, "Key": true, "Value": false},
        {"ColumnName": "DESC1", "DataType": "STRING", "ColumnWidth": "300px", "Visible": true, "Key": false, "Value": true},
        {"ColumnName": "DESC2", "DataType": "STRING", "ColumnWidth": "300px", "Visible": false, "Key": false, "Value": false}
    ]

}